{
    "library": {
        "annotation": [
            {
                "translatorVersion": "0.0.0-dev1",
                "translatorOptions": "",
                "type": "CqlToElmInfo"
            },
            {
                "startLine": 66,
                "startChar": 98,
                "endLine": 66,
                "endChar": 99,
                "message": "extraneous input ',' expecting {<EOF>, 'define', 'context'}",
                "errorType": "SyntaxError",
                "errorSeverity": "Error",
                "type": "CqlToElmError"
            },
            {
                "startLine": 78,
                "startChar": 38,
                "endLine": 78,
                "endChar": 39,
                "message": "extraneous input 'Period' expecting ')'",
                "errorType": "SyntaxError",
                "errorSeverity": "Error",
                "type": "CqlToElmError"
            }
        ],
        "identifier": {
            "id": "Guideline_2zc_VTE3"
        },
        "schemaIdentifier": {
            "id": "urn:hl7-org:elm",
            "version": "r1"
        },
        "usings": {
            "def": [
                {
                    "localIdentifier": "System",
                    "uri": "urn:hl7-org:elm-types:r1"
                },
                {
                    "localIdentifier": "QUICK",
                    "uri": "http://hl7.org/fhir"
                }
            ]
        },
        "parameters": {
            "def": [
                {
                    "name": "Measurement",
                    "accessLevel": "Public",
                    "parameterTypeSpecifier": {
                        "name": "Period",
                        "type": "NamedTypeSpecifier"
                    }
                }
            ]
        },
        "valueSets": {
            "def": [
                {
                    "name": "VTE Diagnosis Valueset",
                    "id": "XYZ",
                    "accessLevel": "Public"
                },
                {
                    "name": "Warfarin Medication Valueset",
                    "id": "XYZ",
                    "accessLevel": "Public"
                },
                {
                    "name": "Inpatient Encounter Valueset",
                    "id": "XYZ",
                    "accessLevel": "Public"
                }
            ]
        },
        "contexts": {
            "def": [
                {
                    "name": "Patient"
                }
            ]
        },
        "statements": {
            "def": [
                {
                    "name": "Patient",
                    "context": "Patient",
                    "expression": {
                        "type": "SingletonFrom",
                        "operand": {
                            "dataType": "{http://hl7.org/fhir}Patient",
                            "type": "Retrieve"
                        }
                    }
                },
                {
                    "name": "Encounters",
                    "context": "Patient",
                    "accessLevel": "Public",
                    "expression": {}
                },
                {
                    "name": "Warfarin Therapy",
                    "context": "Patient",
                    "accessLevel": "Public",
                    "expression": {}
                },
                {
                    "name": "Parenteral Therapy",
                    "context": "Patient",
                    "accessLevel": "Public",
                    "expression": {}
                },
                {
                    "name": "Encounters with Warfarin and Parenteral Therapies",
                    "context": "Patient",
                    "accessLevel": "Public",
                    "expression": {}
                },
                {
                    "name": "Encounters with overlapping Warfarin and Parenteral Therapies",
                    "context": "Patient",
                    "accessLevel": "Public",
                    "expression": {}
                },
                {
                    "name": "Encounters with appropriate overlap therapy",
                    "context": "Patient",
                    "accessLevel": "Public",
                    "expression": {}
                },
                {
                    "name": "overlapDuration",
                    "context": "Patient",
                    "accessLevel": "Public",
                    "expression": {}
                },
                {
                    "name": "Patient has no allergy or intolerance to Penicillin",
                    "context": "Patient",
                    "accessLevel": "Public",
                    "expression": {}
                },
                {
                    "name": "18 or over",
                    "context": "Patient",
                    "accessLevel": "Public",
                    "expression": {}
                },
                {
                    "name": "Comfort Measures Only",
                    "context": "Patient",
                    "accessLevel": "Public",
                    "expression": {}
                },
                {
                    "name": "VTE Diagnosis",
                    "context": "Patient",
                    "accessLevel": "Public",
                    "expression": {}
                },
                {
                    "name": "Denominator",
                    "context": "Patient",
                    "accessLevel": "Public",
                    "expression": {}
                }
            ]
        }
    }
}