{
    "library": {
        "annotation": [
            {
                "translatorVersion": "0.0.0-dev1",
                "translatorOptions": "",
                "type": "CqlToElmInfo"
            }
        ],
        "identifier": {
            "id": "Included",
            "version": "1"
        },
        "schemaIdentifier": {
            "id": "urn:hl7-org:elm",
            "version": "r1"
        },
        "usings": {
            "def": [
                {
                    "localIdentifier": "System",
                    "uri": "urn:hl7-org:elm-types:r1"
                },
                {
                    "localIdentifier": "Simple",
                    "uri": "",
                    "version": "1.0.0"
                }
            ]
        },
        "codeSystems": {
            "def": [
                {
                    "name": "SNOMED",
                    "id": "2.16.840.1.113883.6.96",
                    "accessLevel": "Public"
                }
            ]
        },
        "valueSets": {
            "def": [
                {
                    "name": "Acute Pharyngitis",
                    "id": "2.16.840.1.113883.3.464.1003.102.12.1011",
                    "accessLevel": "Public"
                }
            ]
        }
    }
}