{
    "library": {
        "annotation": [
            {
                "translatorVersion": "2.11.0",
                "translatorOptions": "",
                "type": "CqlToElmInfo"
            },
            {
                "libraryId": "Median_q_diff_units",
                "startLine": 3,
                "startChar": 1,
                "endLine": 3,
                "endChar": 58,
                "message": "Could not load source for library TranslationTestsCommon, version 1.0.",
                "errorType": "include",
                "errorSeverity": "error",
                "targetIncludeLibraryId": "TranslationTestsCommon",
                "targetIncludeLibraryVersionId": "1.0",
                "type": "CqlToElmError"
            },
            {
                "libraryId": "Median_q_diff_units",
                "startLine": 7,
                "startChar": 115,
                "endLine": 7,
                "endChar": 132,
                "message": "Could not resolve library name Common.",
                "errorType": "semantic",
                "errorSeverity": "error",
                "type": "CqlToElmError"
            }
        ],
        "identifier": {
            "id": "Median_q_diff_units"
        },
        "schemaIdentifier": {
            "id": "urn:hl7-org:elm",
            "version": "r1"
        },
        "usings": {
            "def": [
                {
                    "localIdentifier": "System",
                    "uri": "urn:hl7-org:elm-types:r1"
                }
            ]
        },
        "includes": {
            "def": [
                {
                    "localIdentifier": "Common",
                    "path": "TranslationTestsCommon",
                    "version": "1.0"
                }
            ]
        },
        "statements": {
            "def": [
                {
                    "name": "Median_q_diff_units",
                    "context": "Patient",
                    "accessLevel": "Public",
                    "expression": {
                        "type": "Median",
                        "source": {
                            "type": "List",
                            "element": [
                                {
                                    "value": 5,
                                    "unit": "ml",
                                    "type": "Quantity"
                                },
                                {
                                    "value": 0.001,
                                    "unit": "l",
                                    "type": "Quantity"
                                },
                                {
                                    "value": 0.02,
                                    "unit": "dl",
                                    "type": "Quantity"
                                },
                                {
                                    "value": 3,
                                    "unit": "ml",
                                    "type": "Quantity"
                                },
                                {
                                    "value": 4,
                                    "unit": "ml",
                                    "type": "Quantity"
                                },
                                {
                                    "value": 6,
                                    "unit": "ml",
                                    "type": "Quantity"
                                }
                            ]
                        }
                    }
                },
                {
                    "name": "test_Median_q_diff_units",
                    "context": "Patient",
                    "accessLevel": "Public",
                    "expression": {
                        "type": "Null"
                    }
                }
            ]
        }
    }
}