{
    "library": {
        "annotation": [
            {
                "translatorVersion": "0.0.0-dev1",
                "translatorOptions": "",
                "type": "CqlToElmInfo"
            }
        ],
        "identifier": {
            "id": "TestFhirDataProviderDstu3",
            "version": "1.0"
        },
        "schemaIdentifier": {
            "id": "urn:hl7-org:elm",
            "version": "r1"
        },
        "usings": {
            "def": [
                {
                    "localIdentifier": "System",
                    "uri": "urn:hl7-org:elm-types:r1"
                },
                {
                    "localIdentifier": "FHIR",
                    "uri": "http://hl7.org/fhir",
                    "version": "3.0.0"
                }
            ]
        },
        "valueSets": {
            "def": [
                {
                    "name": "Ambulatory Abuse Potential Opioids",
                    "id": "http://hl7.org/fhir/ig/opioid-cds/ValueSet/opioids-abused-in-ambulatory-care",
                    "accessLevel": "Public"
                }
            ]
        },
        "contexts": {
            "def": [
                {
                    "name": "Patient"
                }
            ]
        },
        "statements": {
            "def": [
                {
                    "name": "Patient",
                    "context": "Patient",
                    "expression": {
                        "type": "SingletonFrom",
                        "operand": {
                            "dataType": "{http://hl7.org/fhir}Patient",
                            "type": "Retrieve"
                        }
                    }
                },
                {
                    "name": "MedReqs",
                    "context": "Patient",
                    "accessLevel": "Public",
                    "expression": {}
                },
                {
                    "name": "testChoiceTypes",
                    "context": "Patient",
                    "accessLevel": "Public",
                    "expression": {}
                },
                {
                    "name": "testDateType",
                    "context": "Patient",
                    "accessLevel": "Public",
                    "expression": {}
                },
                {
                    "name": "testFhirObjectEqual",
                    "context": "Patient",
                    "accessLevel": "Public",
                    "expression": {}
                },
                {
                    "name": "testFhirObjectEquivalent",
                    "context": "Patient",
                    "accessLevel": "Public",
                    "expression": {}
                },
                {
                    "name": "Active Ambulatory Opioid Rx",
                    "context": "Patient",
                    "accessLevel": "Public",
                    "expression": {}
                },
                {
                    "name": "GetProvenance",
                    "context": "Patient",
                    "accessLevel": "Public",
                    "expression": {}
                }
            ]
        }
    }
}