{
    "library": {
        "annotation": [
            {
                "translatorVersion": "0.0.0-dev1",
                "translatorOptions": "",
                "type": "CqlToElmInfo"
            }
        ],
        "identifier": {
            "id": "TestHidingVariousUseCases"
        },
        "schemaIdentifier": {
            "id": "urn:hl7-org:elm",
            "version": "r1"
        },
        "usings": {
            "def": [
                {
                    "localIdentifier": "System",
                    "uri": "urn:hl7-org:elm-types:r1"
                },
                {
                    "localIdentifier": "FHIR",
                    "uri": "http://hl7.org/fhir",
                    "version": "4.0.1"
                }
            ]
        },
        "includes": {
            "def": [
                {
                    "localIdentifier": "FHIRHelpers",
                    "version": "4.0.1"
                }
            ]
        },
        "codeSystems": {
            "def": [
                {
                    "name": "CodeSystem",
                    "id": "ABC",
                    "accessLevel": "Public"
                }
            ]
        },
        "valueSets": {
            "def": [
                {
                    "name": "ValueSet",
                    "id": "123",
                    "accessLevel": "Public"
                }
            ]
        },
        "codes": {
            "def": [
                {
                    "name": "Code",
                    "id": "XYZ",
                    "accessLevel": "Public",
                    "codeSystem": {
                        "name": "CodeSystem"
                    }
                }
            ]
        },
        "statements": {
            "def": [
                {
                    "name": "CodeSystemHidden",
                    "accessLevel": "Public"
                },
                {
                    "name": "CodeSystemHidden2",
                    "accessLevel": "Public"
                },
                {
                    "name": "ValueSetHidden",
                    "accessLevel": "Public"
                },
                {
                    "name": "ValueSetHidden2",
                    "accessLevel": "Public"
                },
                {
                    "name": "CodeHidden",
                    "accessLevel": "Public"
                },
                {
                    "name": "CodeHidden2",
                    "accessLevel": "Public"
                },
                {
                    "name": "FHIRHelpersHidden",
                    "accessLevel": "Public"
                },
                {
                    "name": "FHIRHelpersHidden2",
                    "accessLevel": "Public"
                },
                {
                    "name": "FHIRHidden",
                    "accessLevel": "Public"
                },
                {
                    "name": "FHIRHidden2",
                    "accessLevel": "Public"
                },
                {
                    "name": "Definition",
                    "accessLevel": "Public"
                },
                {
                    "name": "AliasHidden",
                    "accessLevel": "Public"
                },
                {
                    "name": "VariableHidden",
                    "accessLevel": "Public"
                }
            ]
        }
    }
}